{"skeleton":{"hash":"hvZYI5DNeN2UjBWHobywF51rfTA","spine":"3.8.75","x":-64.09,"y":-10.68,"width":118.94,"height":99.21,"images":"","audio":""},"bones":[{"name":"root"},{"name":"bf","parent":"root","x":-0.85,"y":112.53},{"name":"bone","parent":"root","y":30.93,"scaleX":0.9,"scaleY":0.9},{"name":"fs","parent":"root","y":70},{"name":"mz","parent":"root","x":-3,"y":35},{"name":"yz","parent":"root","length":32.13,"rotation":-88.63},{"name":"PET6016_shengti","parent":"bone","length":22.83,"rotation":25.83,"x":-33.35,"y":-12.7},{"name":"PET6016_datui2","parent":"PET6016_shengti","length":16.11,"rotation":-156.47,"x":14.28,"y":3.38},{"name":"PET6016_weiba1","parent":"PET6016_shengti","length":29.68,"rotation":98.06,"x":20.74,"y":19.11},{"name":"PET6016_zuotui1","parent":"PET6016_shengti","length":9.99,"rotation":-142.91,"x":22.34,"y":-9.52},{"name":"bone3","parent":"PET6016_shengti","length":29.43,"rotation":-30.22,"x":22.83,"y":-0.04},{"name":"PET6016_tou","parent":"bone3","length":32.51,"rotation":89.54,"x":29.12,"y":0.57},{"name":"PET6016_youshoubi","parent":"bone3","length":18.96,"rotation":-41.37,"x":32.71,"y":-4.46},{"name":"PET6016_youtui2","parent":"PET6016_datui2","length":11.37,"rotation":11.13,"x":16.47,"y":-0.09},{"name":"PET6016_zuoshoubi","parent":"bone3","length":19.72,"rotation":-54.76,"x":0.48,"y":-2.89},{"name":"bone8","parent":"PET6016_zuotui1","length":7.59,"rotation":24.54,"x":9.99,"y":0.02},{"name":"bone9","parent":"PET6016_weiba1","length":36.99,"rotation":15.94,"x":29.68,"y":0.17},{"name":"PET6016_lianjia1","parent":"PET6016_tou","length":32.72,"rotation":-93.17,"x":-7.89,"y":7.35},{"name":"PET6016_yanjingputong","parent":"PET6016_tou","length":9.42,"rotation":-180,"x":4.25,"y":-12.63},{"name":"PET6016_youer","parent":"PET6016_tou","length":22.15,"rotation":66.96,"x":19.37,"y":11.96},{"name":"PET6016_zuikaixin","parent":"PET6016_tou","length":10.44,"rotation":171.49,"x":-11.18,"y":-12.41},{"name":"PET6016_zuoer","parent":"PET6016_tou","length":19.88,"rotation":21.48,"x":21.45,"y":-21.5},{"name":"bone2","parent":"PET6016_youtui2","length":7.62,"rotation":28.51,"x":11.37},{"name":"bone6","parent":"PET6016_zuoshoubi","length":16.78,"rotation":-3.6,"x":19.72,"y":-0.04},{"name":"bone7","parent":"PET6016_youshoubi","length":14.54,"x":18.96,"y":0.02},{"name":"bone4","parent":"PET6016_youer","length":24.13,"rotation":4.95,"x":22.15,"y":-0.06},{"name":"bone5","parent":"PET6016_zuoer","length":25.01,"rotation":-0.9,"x":19.88,"y":0.01}],"slots":[{"name":"pet_yinying","bone":"yz","attachment":"pet_yinying"},{"name":"PET6016_zuotui1","bone":"PET6016_zuotui1","attachment":"PET6016_zuotui1"},{"name":"PET6016_youtui2","bone":"PET6016_youtui2","attachment":"PET6016_youtui2"},{"name":"PET6016_youshoubi","bone":"PET6016_youshoubi","attachment":"PET6016_youshoubi"},{"name":"PET6016_zuoer","bone":"PET6016_zuoer","attachment":"PET6016_zuoer"},{"name":"PET6016_shengti","bone":"PET6016_shengti","attachment":"PET6016_shengti"},{"name":"PET6016_tou","bone":"PET6016_tou","attachment":"PET6016_tou"},{"name":"PET6016_weiba1","bone":"PET6016_weiba1","attachment":"PET6016_weiba1"},{"name":"PET6016_datui2","bone":"PET6016_datui2","attachment":"PET6016_datui2"},{"name":"PET6016_youer","bone":"PET6016_youer","attachment":"PET6016_youer"},{"name":"PET6016_zuikaixin","bone":"PET6016_zuikaixin","attachment":"PET6016_zuikaixin"},{"name":"PET6016_yanjingputong","bone":"PET6016_yanjingputong","attachment":"PET6016_yanjingputong"},{"name":"PET6016_lianjia1","bone":"PET6016_lianjia1","attachment":"PET6016_lianjia1"},{"name":"PET6016_zuoshoubi","bone":"PET6016_zuoshoubi","attachment":"PET6016_zuoshoubi"}],"skins":[{"name":"default","attachments":{"PET6016_youshoubi":{"PET6016_youshoubi":{"type":"mesh","uvs":[0.22644,0.05644,0.11024,0.15244,0.04706,0.36578,0.12061,0.57011,0.25148,0.74344,0.41147,0.84093,0.4681,0.87544,0.51346,0.898,0.71856,1,0.82799,1,0.84921,0.98797,0.94532,0.92477,0.87989,0.72744,0.81784,0.5541,0.72322,0.43657,0.61927,0.30744,0.34008,0.04852,0.55932,0.63819],"triangles":[9,8,10,10,8,17,12,10,17,7,17,8,10,12,11,12,17,13,7,6,17,6,5,17,17,14,13,5,4,17,4,3,17,1,15,17,15,1,16,17,15,14,16,1,0,2,17,3,2,1,17],"vertices":[1,12,-3.79,4.08,1,1,12,-4.68,-1.37,1,1,12,-1.35,-8.05,1,1,12,5.47,-10.69,1,2,12,13.13,-11.03,0.9563,24,-5.83,-11.06,0.04369,2,12,19.79,-8.8,0.56513,24,0.82,-8.83,0.43486,2,12,22.14,-8.01,0.32765,24,3.17,-8.04,0.67234,2,12,23.91,-7.26,0.17183,24,4.94,-7.29,0.82816,1,24,12.93,-3.91,1,1,24,15.91,-0.85,1,1,24,16.2,0.01,1,1,24,17.32,4.15,1,2,12,29.84,6.9,0.0028,24,10.87,6.87,0.99719,2,12,24.06,9.15,0.14165,24,5.09,9.12,0.85834,2,12,18.7,9.21,0.52553,24,-0.26,9.18,0.47446,2,12,12.82,9.28,0.9085,24,-6.14,9.25,0.09149,1,12,-0.89,7.43,1,2,12,19.01,0,0.5,24,0.04,-0.03,0.5],"hull":17,"edges":[0,2,2,4,4,6,6,8,16,18,22,24,24,26,30,32,0,32,2,34,18,20,20,22,34,20,26,28,28,30,12,14,14,16,8,10,10,12],"width":39,"height":33}},"pet_yinying":{"pet_yinying":{"x":-1.3,"y":0.88,"scaleX":0.9,"rotation":88.63,"width":120,"height":24}},"PET6016_datui2":{"PET6016_datui2":{"x":12.72,"y":-3.12,"rotation":130.63,"width":39,"height":36}},"PET6016_zuikaixin":{"PET6016_zuibizui":{"x":-1.5,"y":2.17,"rotation":103.35,"width":26,"height":27},"PET6016_zuigongji":{"x":-1.5,"y":2.17,"rotation":103.35,"width":26,"height":27},"PET6016_zuikaixin":{"x":-1.5,"y":2.17,"rotation":103.35,"width":26,"height":27},"PET6016_zuisiwang":{"x":-1.5,"y":2.17,"rotation":103.35,"width":26,"height":27},"PET6016_zuixuli":{"x":-1.5,"y":2.17,"rotation":103.35,"width":26,"height":27}},"PET6016_weiba1":{"PET6016_weiba1":{"type":"mesh","uvs":[0.10033,0.05387,0.05792,0.51257,0.52204,0.52184,0.39246,0.70254,0.64219,0.7952,0.58565,0.90872,0.92019,0.94579,0.94375,0.84849,0.78119,0.8091,0.83773,0.74192,0.68931,0.58439,0.83773,0.24847,0.47963,0.0585],"triangles":[6,5,8,5,4,8,6,8,7,9,8,10,3,2,4,8,4,10,4,2,10,10,2,11,2,1,12,1,0,12,2,12,11],"vertices":[1,16,38.9,-1.08,1,1,16,23.05,21.55,1,2,16,1.77,4.31,0.57722,8,30.2,4.81,0.42276,1,8,25.46,17.2,1,1,8,12.63,8.06,1,1,8,8.83,14.63,1,1,8,-4,-0.51,1,1,8,0.06,-4.92,1,1,8,7.37,1.72,1,1,8,8.85,-3.29,1,1,8,21.58,-1.28,1,2,16,-1.87,-20.23,0.85337,8,33.44,-19.79,0.14662,1,16,21.62,-15.31,1],"hull":13,"edges":[0,2,2,4,4,6,6,8,8,10,10,12,12,14,14,16,16,18,18,20,20,22,22,24,0,24],"width":59,"height":60},"PET6016_weiba2":{"type":"mesh","uvs":[0.10033,0.05387,0.05792,0.51257,0.52204,0.52184,0.39246,0.70254,0.64219,0.7952,0.58565,0.90872,0.92019,0.94579,0.94375,0.84849,0.78119,0.8091,0.83773,0.74192,0.68931,0.58439,0.83773,0.24847,0.47963,0.0585],"triangles":[6,5,8,5,4,8,6,8,7,9,8,10,3,2,4,8,4,10,4,2,10,10,2,11,2,1,12,1,0,12,2,12,11],"vertices":[1,16,38.9,-1.08,1,1,16,23.05,21.55,1,2,16,1.77,4.31,0.57722,8,30.2,4.81,0.42276,1,8,25.46,17.2,1,1,8,12.63,8.06,1,1,8,8.83,14.63,1,1,8,-4,-0.51,1,1,8,0.06,-4.92,1,1,8,7.37,1.72,1,1,8,8.85,-3.29,1,1,8,21.58,-1.28,1,2,16,-1.87,-20.23,0.85337,8,33.44,-19.79,0.14662,1,16,21.62,-15.31,1],"hull":13,"edges":[0,2,2,4,4,6,6,8,8,10,10,12,12,14,14,16,16,18,18,20,20,22,22,24,0,24],"width":59,"height":60}},"PET6016_lianjia1":{"PET6016_lianjia1":{"x":13.68,"y":-0.58,"rotation":8.02,"width":55,"height":24},"PET6016_lianjia2":{"x":13.68,"y":-0.58,"rotation":8.02,"width":55,"height":24}},"PET6016_zuotui1":{"PET6016_zuotui1":{"type":"mesh","uvs":[0.67088,0.09339,0.49374,0.23948,0.3604,0.48817,0.35713,0.57486,0.34897,0.79078,0.38326,0.88643,0.55469,0.93165,0.73755,0.88121,0.74707,0.71252,0.68802,0.64121,0.70124,0.5348,0.70897,0.47252,0.91088,0.21339,0.8385,0.07948,0.54896,0.53341],"triangles":[8,7,6,4,6,5,14,9,6,14,6,4,14,4,3,8,6,9,9,14,10,3,2,14,10,14,11,11,13,12,14,2,1,14,1,0,13,14,0,11,14,13],"vertices":[1,9,-0.37,-2.32,1,1,9,4.3,-4.11,1,2,9,10.67,-3.99,0.5509,15,-1.04,-3.94,0.44909,2,9,12.48,-3.15,0.221,15,0.94,-3.92,0.77899,1,15,5.91,-3.87,1,1,15,8.08,-3.05,1,1,15,8.96,0.58,1,1,15,7.63,4.37,1,2,9,11.57,5.57,0.00313,15,3.75,4.39,0.99686,2,9,10.67,3.72,0.10544,15,2.16,3.08,0.89455,2,9,8.37,2.86,0.70371,15,-0.29,3.25,0.29628,2,9,7.02,2.35,0.9498,15,-1.72,3.35,0.05019,1,9,-0.21,3.41,1,1,9,-2.26,0.66,1,2,9,9.8,0,0.5,15,-0.18,0.05,0.5],"hull":14,"edges":[0,2,2,4,8,10,10,12,12,14,14,16,16,18,22,24,24,26,0,26,26,28,28,12,4,6,6,8,18,20,20,22],"width":21,"height":23}},"PET6016_zuoer":{"PET6016_zuoer":{"type":"mesh","uvs":[0.27079,0.05733,0.16226,0.07741,0.20167,0.50439,0.25098,0.56007,0.42685,0.75864,0.75055,0.96038,0.82756,0.95058,0.90255,0.94104,0.91944,0.71995,0.84907,0.48366,0.76979,0.41249,0.35648,0.04148,0.51129,0.50024],"triangles":[6,5,12,8,6,12,4,12,5,7,6,8,12,9,8,10,9,12,4,3,12,3,2,12,2,0,12,2,1,0,0,11,12,12,11,10],"vertices":[1,26,25.13,-0.35,1,1,26,24.86,2.76,1,2,26,1.97,8.1,0.71431,21,21.98,8.09,0.28568,2,26,-1.33,7.65,0.40494,21,18.67,7.69,0.59504,1,21,6.84,6.26,1,1,21,-6.28,1.06,1,1,21,-6.36,-1.07,1,1,21,-6.43,-3.17,1,1,21,5.08,-7.08,1,2,26,-1.66,-9.02,0.31331,21,18.07,-8.98,0.68668,2,26,2.68,-8.02,0.67819,21,22.44,-8.05,0.3218,1,26,25.34,-2.81,1,2,26,-0.07,0,0.5,21,19.81,0.01,0.5],"hull":12,"edges":[2,4,8,10,14,16,16,18,2,0,0,22,0,24,10,12,12,14,24,12,4,6,6,8,18,20,20,22],"width":27,"height":55}},"PET6016_youtui2":{"PET6016_youtui2":{"type":"mesh","uvs":[0.59054,0.29681,0.54797,0.27174,0.41745,0.36799,0.35291,0.54137,0.33324,0.59424,0.32641,0.65023,0.30903,0.79271,0.35534,0.89271,0.42903,0.92646,0.51324,0.90521,0.54587,0.83521,0.52271,0.70146,0.52962,0.62641,0.5364,0.55271,0.62377,0.3777,0.60903,0.3077,0.43952,0.61018],"triangles":[9,8,10,8,11,10,6,8,7,8,16,11,16,8,5,6,5,8,11,16,12,5,4,16,12,16,13,4,3,16,0,14,13,16,3,2,15,14,0,2,0,16,0,2,1,16,0,13],"vertices":[1,13,-0.41,0,1,1,13,-0.31,-1.8,1,1,13,4.81,-4.6,1,2,13,10.84,-4.01,0.7341,22,-2.38,-3.28,0.26589,2,13,12.68,-3.82,0.43508,22,-0.67,-3.99,0.56491,2,13,14.37,-3.17,0.17489,22,1.11,-4.22,0.8251,1,22,5.68,-4.81,1,1,22,8.85,-2.99,1,1,22,9.88,-0.17,1,1,22,9.15,3,1,1,22,6.89,4.21,1,2,13,12.12,4.12,0.10291,22,2.62,3.25,0.89708,2,13,9.9,3.17,0.62487,22,0.22,3.47,0.37512,2,13,7.72,2.23,0.9876,22,-2.13,3.69,0.01239,1,13,1.22,2.36,0.99999,1,13,-0.45,0.77,0.99999,2,13,11.14,-0.06,0.5,22,-0.23,0.04,0.5],"hull":16,"edges":[2,4,12,14,14,16,16,18,18,20,20,22,26,28,28,30,2,0,0,30,0,32,32,16,4,6,6,8,8,10,10,12,22,24,24,26],"width":38,"height":32}},"PET6016_youer":{"PET6016_youer":{"type":"mesh","uvs":[0.07843,0.22559,0.07308,0.26512,0.37286,0.67182,0.45662,0.73246,0.63674,0.86284,0.8284,0.89057,0.9092,0.78869,0.98356,0.69493,0.79567,0.4315,0.62419,0.31324,0.50751,0.23277,0.09057,0.13572,0.51279,0.48542],"triangles":[5,4,6,3,12,4,4,12,6,12,8,6,6,8,7,12,9,8,3,2,12,2,1,12,12,1,0,0,10,12,12,10,9,0,11,10],"vertices":[1,25,25.37,0.32,1,1,25,25.07,1.78,1,2,25,4.29,9.33,0.78412,19,25.63,9.6,0.21587,2,25,-0.74,9.63,0.37792,19,20.58,9.47,0.62207,2,25,-11.57,10.28,9.0E-5,19,9.73,9.18,0.9999,1,19,0.1,5.24,1,1,19,-1.98,-0.12,1,1,19,-3.91,-5.06,1,1,19,9.61,-8.93,1,2,25,-3.02,-8.17,0.24638,19,19.84,-8.47,0.75361,2,25,3.93,-8.46,0.83955,19,26.8,-8.15,0.16044,1,25,26.06,-2.99,1,2,25,0.02,0.03,0.5,19,22.18,-0.02,0.5],"hull":12,"edges":[2,4,8,10,14,16,20,22,2,0,0,22,0,24,10,12,12,14,24,12,4,6,6,8,16,18,18,20],"width":54,"height":37}},"PET6016_zuoshoubi":{"PET6016_zuoshoubi":{"type":"mesh","uvs":[0.26283,0.09213,0.19795,0.12398,0.12818,0.30495,0.15216,0.46193,0.25074,0.64712,0.29607,0.73229,0.36273,0.78909,0.60567,0.99611,0.79318,1,0.93708,0.9198,0.86949,0.85439,0.89129,0.62981,0.79504,0.42437,0.74521,0.31803,0.6817,0.25017,0.49011,0.04549,0.31787,0.06511,0.55553,0.57096],"triangles":[8,10,9,10,8,17,17,8,7,7,6,17,10,17,11,6,5,17,17,12,11,5,4,17,4,3,17,0,2,1,17,2,0,17,0,14,14,0,16,17,13,12,17,14,13,14,16,15,17,3,2],"vertices":[1,14,-1.66,-0.32,1,1,14,-1.9,-3.13,1,1,14,2.76,-9.08,1,2,14,8.5,-11.42,0.97294,23,-10.48,-12.05,0.02705,2,14,16.67,-11.82,0.68779,23,-2.3,-11.94,0.3122,2,14,20.43,-12,0.45906,23,1.45,-11.89,0.54092,2,14,23.66,-10.91,0.25788,23,4.61,-10.59,0.74211,1,23,16.12,-5.86,1,1,23,19.6,0.56,0.99999,1,23,19.39,6.99,1,1,23,15.92,5.81,1,2,14,28.89,9.97,0.05114,23,8.52,10.57,0.94885,2,14,20.09,10.85,0.51305,23,-0.31,10.9,0.48694,2,14,15.53,11.31,0.80149,23,-4.89,11.07,0.1985,2,14,11.99,10.54,0.93112,23,-8.38,10.08,0.06887,1,14,1.31,8.21,1,1,14,-1.47,2.05,1,2,14,20.21,-0.09,0.5,23,0.49,-0.01,0.5],"hull":17,"edges":[2,4,4,6,14,16,16,18,18,20,20,22,30,32,2,0,0,32,0,34,34,16,6,8,8,10,10,12,12,14,22,24,24,26,26,28,28,30],"width":39,"height":39}},"PET6016_yanjingputong":{"PET6016_yanjingbiyan":{"x":1.81,"y":-1.65,"rotation":94.84,"width":39,"height":20},"PET6016_yanjinggongji":{"x":1.81,"y":-1.65,"rotation":94.84,"width":39,"height":20},"PET6016_yanjingputong":{"x":1.81,"y":-1.65,"rotation":94.84,"width":39,"height":20},"PET6016_yanjingshouji":{"x":1.81,"y":-1.65,"rotation":94.84,"width":39,"height":20},"PET6016_yanjingsiwang":{"x":1.81,"y":-1.65,"rotation":94.84,"width":39,"height":20},"PET6016_yanjingxuli":{"x":1.81,"y":-1.65,"rotation":94.84,"width":39,"height":20}},"PET6016_tou":{"PET6016_tou":{"x":2.81,"y":-4.18,"rotation":-85.15,"width":53,"height":54}},"PET6016_shengti":{"PET6016_shengti":{"type":"mesh","uvs":[0.02603,0.57706,0.04381,0.44014,0.14726,0.22751,0.31475,0.08162,0.4121,0.03433,0.51954,0.02223,0.70361,0.04458,0.89661,0.18949,0.94025,0.33198,0.97177,0.84739,0.87155,0.96762,0.68647,0.97096,0.54119,0.86458,0.45355,0.85332,0.33396,0.85499,0.19394,0.84392,0.05856,0.7472,0.44505,0.46516],"triangles":[7,17,6,8,17,7,17,4,5,17,12,13,6,17,5,9,17,8,9,12,17,9,11,12,10,11,9,3,4,17,2,3,17,1,2,17,17,0,1,15,16,0,17,15,0,14,15,17,13,14,17],"vertices":[1,6,-6.64,7.9,1,1,6,-2.31,13.86,1,3,6,9.38,20.72,0.95783,10,-22.07,11.18,0.0419,11,10.19,51.28,2.6E-4,3,6,23.76,22.36,0.67639,10,-10.47,19.83,0.29872,11,18.93,39.75,0.02487,3,6,31.25,21.52,0.46352,10,-3.58,22.88,0.4657,11,22.03,32.88,0.07075,3,6,38.59,18.69,0.24861,10,4.18,24.12,0.57663,11,23.34,25.12,0.17474,3,6,50.17,11.77,0.02758,10,17.67,23.97,0.41376,11,23.3,11.63,0.55865,2,6,59.51,-1.27,3.0E-5,11,16.84,-3.05,0.99996,1,11,9.59,-6.86,0.99999,2,10,40.46,-16.94,0.91426,11,-17.43,-11.47,0.08573,2,10,33.65,-23.86,0.97053,11,-24.4,-4.73,0.02946,2,6,27.67,-31.88,0.01646,10,20.2,-25.07,0.98353,2,6,20.57,-22.18,0.16421,10,9.19,-20.27,0.83578,2,6,15.07,-18.86,0.42659,10,2.76,-20.16,0.5734,2,6,7.18,-15.14,0.8106,10,-5.92,-20.92,0.18939,2,6,-1.76,-10.16,0.98721,10,-16.16,-21.12,0.01278,1,6,-8.43,-1.25,1,2,6,23.47,-0.07,0.5,10,0.56,0.29,0.5],"hull":17,"edges":[0,2,2,4,12,14,14,16,16,18,18,20,20,22,30,32,0,32,22,24,24,26,8,10,10,12,4,6,6,8,26,28,28,30],"width":73,"height":53}}}}],"animations":{"attack01":{"slots":{"PET6016_zuikaixin":{"attachment":[{"time":0.2667,"name":"PET6016_zuibizui"},{"time":0.7,"name":"PET6016_zuigongji"},{"time":1.3,"name":"PET6016_zuikaixin"}]},"PET6016_lianjia1":{"color":[{"color":"ffffff00"},{"time":0.7,"color":"ffffffff"},{"time":0.8,"color":"ffffff00"},{"time":0.9,"color":"ffffffff"},{"time":0.9667,"color":"ffffff00"}],"attachment":[{"time":0.7,"name":"PET6016_lianjia2"},{"time":1.3,"name":"PET6016_lianjia1"}]},"PET6016_yanjingputong":{"attachment":[{"time":0.2667,"name":"PET6016_yanjingbiyan"},{"time":0.7,"name":"PET6016_yanjinggongji"},{"time":1.3,"name":"PET6016_yanjingputong"}]}},"bones":{"PET6016_weiba1":{"rotate":[{},{"time":0.2667,"angle":12.38},{"time":0.6667,"angle":61.35},{"time":0.7,"angle":-47.62},{"time":0.7333,"angle":-29.34},{"time":0.7667,"angle":-35.35,"curve":"stepped"},{"time":1.0333,"angle":-35.35},{"time":1.3}]},"PET6016_youshoubi":{"rotate":[{},{"time":0.2667,"angle":-27},{"time":0.4,"angle":2.42},{"time":0.6667,"angle":12.23},{"time":0.7,"angle":1.46},{"time":1.0333,"angle":2.94},{"time":1.3}],"translate":[{},{"time":0.2667,"x":1.26,"y":-3.78},{"time":0.4,"x":-0.74,"y":0.29},{"time":0.6667,"x":-1.41,"y":1.65},{"time":0.7}]},"bone7":{"rotate":[{},{"time":0.2667,"angle":5.85},{"time":0.4,"angle":15.88},{"time":0.6667,"angle":19.22},{"time":0.7,"angle":3.18,"curve":"stepped"},{"time":1.0333,"angle":3.18},{"time":1.3}],"translate":[{"time":0.2667},{"time":0.4,"x":0.01,"y":0.45},{"time":0.6667,"x":0.02,"y":0.6},{"time":0.7}]},"bone3":{"rotate":[{},{"time":0.2667,"angle":9.95},{"time":0.4,"angle":5.7},{"time":0.6667,"angle":4.29},{"time":0.7,"angle":3.57,"curve":"stepped"},{"time":1.0333,"angle":3.57},{"time":1.3}]},"PET6016_zuoer":{"rotate":[{},{"time":0.2667,"angle":16.69},{"time":0.4667,"angle":-7.45},{"time":0.6667,"angle":19.84},{"time":0.8667,"angle":-0.7},{"time":1.0667,"angle":28.32},{"time":1.3}]},"bone6":{"rotate":[{},{"time":0.2667,"angle":18.48},{"time":0.4,"angle":15.09},{"time":0.6667,"angle":13.97},{"time":0.7,"angle":20.41},{"time":1.0333,"angle":19.92},{"time":1.3}],"translate":[{"time":0.2667},{"time":0.4,"x":-1.58,"y":-0.37},{"time":0.6667,"x":-2.11,"y":-0.5},{"time":0.7}]},"bone4":{"rotate":[{},{"time":0.2667,"angle":8.96},{"time":0.4667,"angle":-8.5},{"time":0.6667,"angle":2.52},{"time":0.8667,"angle":2.21},{"time":1.0667,"angle":20.35},{"time":1.3}]},"PET6016_tou":{"rotate":[{},{"time":0.2667,"angle":1.79},{"time":0.4,"angle":-6.02},{"time":0.6667,"angle":-2.85},{"time":0.7}]},"yz":{"translate":[{"time":0.2667},{"time":0.6667,"x":-7},{"time":0.7,"x":12.09},{"time":1.0333,"x":12.29},{"time":1.3}],"scale":[{},{"time":0.2667,"y":1.1,"curve":"stepped"},{"time":0.6667,"y":1.1},{"time":0.7},{"time":1.0333,"y":1.1},{"time":1.3}]},"PET6016_zuotui1":{"rotate":[{},{"time":0.2667,"angle":5.73},{"time":0.4,"angle":0.23},{"time":0.6667,"angle":-1.59},{"time":0.7},{"time":1.0333,"angle":-4.93},{"time":1.3}],"translate":[{},{"time":0.2667,"x":-4.04,"y":1.46},{"time":0.4,"x":5.32,"y":3.33},{"time":0.6667,"x":8.44,"y":3.95},{"time":0.7}]},"bone9":{"rotate":[{},{"time":0.2667,"angle":-24.06},{"time":0.6667,"angle":-37.27},{"time":0.7,"angle":-2.04,"curve":"stepped"},{"time":1.0333,"angle":-2.04},{"time":1.3}]},"PET6016_youer":{"rotate":[{},{"time":0.2667,"angle":8.96},{"time":0.4667,"angle":-8.5},{"time":0.6667,"angle":2.52},{"time":0.8667,"angle":-31.93},{"time":1.0667,"angle":7.63},{"time":1.3}]},"PET6016_datui2":{"rotate":[{"time":0.2667},{"time":0.4,"angle":8.15},{"time":0.6667,"angle":10.87},{"time":0.7,"angle":-6.75},{"time":1.0333,"angle":-8.68},{"time":1.3}],"translate":[{"time":0.2667},{"time":0.4,"x":0.3,"y":1.58},{"time":0.6667,"x":0.4,"y":2.11},{"time":0.7,"x":-2.24,"y":-1.84,"curve":"stepped"},{"time":1.0333,"x":-2.24,"y":-1.84},{"time":1.3}]},"bone":{"translate":[{},{"time":0.2667,"x":5},{"time":0.4,"x":-6.24,"y":-2.25},{"time":0.6667,"x":-10,"y":-3},{"time":0.7,"x":10,"y":-1},{"time":1.0333,"x":11,"y":-2},{"time":1.3}]},"bone8":{"rotate":[{},{"time":0.2667,"angle":-8.42},{"time":0.4,"angle":12.04},{"time":0.6667,"angle":18.86},{"time":0.7}]},"PET6016_shengti":{"rotate":[{},{"time":0.2667,"angle":2.22},{"time":0.4,"angle":-7.43},{"time":0.6667,"angle":-10.65},{"time":0.7,"angle":-2.19,"curve":"stepped"},{"time":1.0333,"angle":-2.19},{"time":1.3}]},"bone5":{"rotate":[{},{"time":0.2667,"angle":16.69},{"time":0.4667,"angle":-7.45},{"time":0.6667,"angle":19.84},{"time":0.8667,"angle":-0.7},{"time":1.0667,"angle":20.78},{"time":1.3}]},"PET6016_zuoshoubi":{"rotate":[{},{"time":0.2667,"angle":-26.26},{"time":0.4,"angle":4.82},{"time":0.6667,"angle":15.18},{"time":0.7,"angle":-2.39},{"time":1.0333,"angle":-1.12},{"time":1.3}],"translate":[{},{"time":0.2667,"x":-2.9,"y":1.21},{"time":0.4,"x":-0.71,"y":1.75},{"time":0.6667,"x":0.01,"y":1.93},{"time":0.7},{"time":1.0333,"x":-1.27,"y":0.29},{"time":1.3}]},"PET6016_youtui2":{"rotate":[{},{"time":0.2667,"angle":-3},{"time":0.4,"angle":11.32},{"time":0.6667,"angle":16.1},{"time":0.7,"angle":-3.24,"curve":"stepped"},{"time":1.0333,"angle":-3.24},{"time":1.3}],"translate":[{},{"time":0.2667,"x":2.99,"y":-1.94},{"time":0.4,"x":-1.66,"y":-1.6},{"time":0.6667,"x":-3.21,"y":-1.49},{"time":0.7}]},"bone2":{"rotate":[{},{"time":0.2667,"angle":-9.02},{"time":0.4,"angle":7.02},{"time":0.6667,"angle":12.38},{"time":0.7,"angle":-20.72,"curve":"stepped"},{"time":1.0333,"angle":-20.72},{"time":1.3}]},"fs":{"translate":[{"x":-61.14,"y":20.61},{"time":0.2667,"x":-65.38,"y":18.12},{"time":0.6667,"x":-80.62,"y":-8.72},{"time":0.7,"x":21.76,"y":32.14}]}}},"dead":{"slots":{"PET6016_zuikaixin":{"attachment":[{"time":0.3333,"name":"PET6016_zuisiwang"}]},"PET6016_lianjia1":{"color":[{"color":"ffffff00"}]},"PET6016_yanjingputong":{"attachment":[{"time":0.3667,"name":"PET6016_yanjingsiwang"}]}},"bones":{"PET6016_weiba1":{"rotate":[{},{"time":0.2,"angle":-4.3},{"time":0.3667},{"time":0.6,"angle":35.85},{"time":0.8,"angle":-0.15},{"time":1.0333,"angle":43.01},{"time":1.2,"angle":41.53},{"time":1.4333,"angle":46.57}],"translate":[{},{"time":0.8,"x":2.45,"y":-0.54}]},"PET6016_zuikaixin":{"scale":[{},{"time":0.3667,"x":0.8}]},"PET6016_zuotui1":{"rotate":[{},{"time":0.3667,"angle":-8.27},{"time":0.6},{"time":0.7333,"angle":-1.24},{"time":0.8,"angle":319.54},{"time":1.4333,"angle":-40.45}],"translate":[{},{"time":0.3667,"x":0.9,"y":1.87},{"time":0.6}]},"bone7":{"rotate":[{},{"time":0.3667,"angle":-3.68},{"time":0.6,"angle":10.19},{"time":0.8},{"time":1.1333,"angle":-1.74},{"time":1.4333}],"translate":[{},{"time":0.3667,"x":0.02,"y":0.6},{"time":0.6}]},"PET6016_shengti":{"rotate":[{},{"time":0.3667,"angle":-2.59},{"time":0.6,"angle":2.22},{"time":0.8}]},"bone9":{"rotate":[{},{"time":0.2,"angle":-9.23},{"time":0.3667},{"time":0.6,"angle":37.09},{"time":0.8,"angle":1.8},{"time":1.0333,"angle":45.5},{"time":1.2,"angle":43.88},{"time":1.4333,"angle":49.05}]},"bone":{"rotate":[{"time":0.6},{"time":0.8,"angle":0.71}],"translate":[{},{"time":0.3667,"y":-3},{"time":0.6},{"time":0.7333,"x":0.57,"y":-1.19},{"time":0.8,"x":1.01,"y":-10.8},{"time":0.9667,"x":1.01,"y":-12.12},{"time":1.1667,"x":1.01,"y":-9.79},{"time":1.4333,"x":1.01,"y":-11.9}]},"bone4":{"rotate":[{},{"time":0.3,"angle":-6.15},{"time":0.6,"angle":18.38},{"time":0.8,"angle":-4.15},{"time":1.0333,"angle":21.34},{"time":1.2,"angle":13.76},{"time":1.4333,"angle":16.11}]},"PET6016_tou":{"rotate":[{},{"time":0.1667,"angle":5.26},{"time":0.3667,"angle":-7.78},{"time":0.6,"angle":7.03},{"time":0.8,"angle":0.18},{"time":1.1333,"angle":-1.81},{"time":1.4333}]},"yz":{"translate":[{},{"time":0.3667,"x":0.6,"y":0.22},{"time":0.6333,"x":1.48,"y":-1.41},{"time":0.8,"x":2.02,"y":-2.43}],"scale":[{},{"time":0.3667,"y":1.1},{"time":0.6333,"y":0.9},{"time":0.8,"y":1.2},{"time":1.1,"y":1.1},{"time":1.4333,"y":1.2}]},"PET6016_youer":{"rotate":[{},{"time":0.3,"angle":-7.02},{"time":0.6,"angle":16.64},{"time":0.8,"angle":-20.24},{"time":1.0333,"angle":32.78},{"time":1.2,"angle":25.19},{"time":1.4333,"angle":27.54}]},"bone5":{"rotate":[{},{"time":0.3,"angle":-8.8},{"time":0.6,"angle":13.08},{"time":0.8,"angle":-10.04},{"time":1.0333,"angle":27.6},{"time":1.2,"angle":20.17},{"time":1.4333,"angle":22.36}]},"PET6016_zuoshoubi":{"rotate":[{},{"time":0.3667,"angle":-3.89},{"time":0.6,"angle":-12.66},{"time":0.7333,"angle":-0.33},{"time":0.8,"angle":26.4},{"time":1.1333,"angle":24.59},{"time":1.4333,"angle":26.4}],"translate":[{},{"time":0.3667,"x":0.01,"y":1.93},{"time":0.6}]},"PET6016_youtui2":{"rotate":[{},{"time":0.3667,"angle":3.65},{"time":0.6},{"time":0.7333,"angle":3.97},{"time":0.8,"angle":-31.32},{"time":1.1333,"angle":-27.94},{"time":1.4333,"angle":-31.32}],"translate":[{},{"time":0.3667,"x":-0.71,"y":-0.17},{"time":0.6}]},"bone3":{"rotate":[{},{"time":0.3667,"angle":2.73},{"time":0.6,"angle":7.23},{"time":0.8}]},"bone2":{"rotate":[{},{"time":0.3667,"angle":12.38},{"time":0.6,"curve":"stepped"},{"time":0.8},{"time":1.1333,"angle":3.38},{"time":1.4333}]},"PET6016_zuoer":{"rotate":[{},{"time":0.3,"angle":3.32},{"time":0.6,"angle":37.35},{"time":0.8,"angle":6.15},{"time":1.0333,"angle":48.97},{"time":1.2,"angle":41.54},{"time":1.4333,"angle":43.73}],"translate":[{},{"time":1.0333,"x":-0.1,"y":1.41}]},"PET6016_datui2":{"rotate":[{},{"time":0.3667,"angle":-4.31},{"time":0.6},{"time":0.8,"angle":-12.64},{"time":1.1333,"angle":-9.25},{"time":1.4333,"angle":-12.64}],"translate":[{},{"time":0.3667,"y":0.63},{"time":0.6}]},"PET6016_youshoubi":{"rotate":[{},{"time":0.3667,"angle":4.82},{"time":0.6,"angle":-23.62},{"time":0.7333,"angle":-5.14},{"time":0.8,"angle":26.21},{"time":1.1333,"angle":24.47},{"time":1.4333,"angle":26.21}],"translate":[{},{"time":0.3667,"x":-1.41,"y":1.65},{"time":0.6,"x":1.14,"y":-3.15},{"time":0.8}]},"bone8":{"rotate":[{},{"time":0.3667,"angle":18.86},{"time":0.6},{"time":0.8,"angle":-54.4}]},"bone6":{"rotate":[{},{"time":0.3667,"angle":9.49},{"time":0.6,"angle":2.17},{"time":0.8,"angle":6.29},{"time":1.1333,"angle":4.48},{"time":1.4333,"angle":6.29}],"translate":[{},{"time":0.3667,"x":-2.11,"y":-0.5},{"time":0.6}]}}},"hurt":{"slots":{"PET6016_zuikaixin":{"attachment":[{"time":0.1667,"name":"PET6016_zuixuli"},{"time":0.9333,"name":"PET6016_zuikaixin"}]},"PET6016_lianjia1":{"color":[{"color":"ffffff00"}]},"PET6016_yanjingputong":{"attachment":[{"time":0.1667,"name":"PET6016_yanjingshouji"},{"time":0.9333,"name":"PET6016_yanjingputong"}]}},"bones":{"PET6016_weiba1":{"rotate":[{},{"time":0.1667,"angle":11.58},{"time":0.3333,"angle":2},{"time":0.5333,"angle":-4.44},{"time":0.7333,"angle":11.58},{"time":0.9333}]},"PET6016_youshoubi":{"rotate":[{},{"time":0.1667,"angle":4.82},{"time":0.2333,"angle":5.29},{"time":0.5333,"angle":11.77},{"time":0.7333,"angle":4.82},{"time":0.9333}],"translate":[{},{"time":0.1667,"x":-1.41,"y":1.65},{"time":0.2333,"curve":"stepped"},{"time":0.5333},{"time":0.7333,"x":-1.41,"y":1.65},{"time":0.9333}]},"bone7":{"rotate":[{},{"time":0.1667,"angle":-3.68},{"time":0.2333,"angle":5.29,"curve":"stepped"},{"time":0.5333,"angle":5.29},{"time":0.7333,"angle":-3.68},{"time":0.9333}],"translate":[{},{"time":0.1667,"x":0.02,"y":0.6},{"time":0.2333,"curve":"stepped"},{"time":0.5333},{"time":0.7333,"x":0.02,"y":0.6},{"time":0.9333}]},"PET6016_tou":{"rotate":[{},{"time":0.1667,"angle":-9.57},{"time":0.2333,"angle":-4.21,"curve":"stepped"},{"time":0.5333,"angle":-4.21},{"time":0.7333,"angle":-9.57},{"time":0.9333}]},"bone9":{"rotate":[{},{"time":0.1667,"angle":11.58},{"time":0.3333,"angle":2},{"time":0.5333,"angle":-4.44},{"time":0.7333,"angle":11.58},{"time":0.9333}]},"PET6016_youer":{"rotate":[{},{"time":0.1667,"angle":17.59},{"time":0.5333,"angle":-4.99},{"time":0.7333,"angle":17.59},{"time":0.9333}]},"bone8":{"rotate":[{},{"time":0.1667,"angle":18.86},{"time":0.2333,"angle":-6.73,"curve":"stepped"},{"time":0.5333,"angle":-6.73},{"time":0.7333,"angle":18.86},{"time":0.9333}]},"bone5":{"rotate":[{},{"time":0.1667,"angle":16.22},{"time":0.5333,"angle":10.47},{"time":0.7333,"angle":16.22},{"time":0.9333}]},"bone":{"translate":[{},{"time":0.1667,"y":-3},{"time":0.2333,"x":-10},{"time":0.5333,"x":-20},{"time":0.7333,"y":-3},{"time":0.9333}]},"PET6016_zuoshoubi":{"rotate":[{},{"time":0.1667,"angle":-3.89},{"time":0.2333,"angle":20.1},{"time":0.5333,"angle":26.58},{"time":0.7333,"angle":-3.89},{"time":0.9333}],"translate":[{},{"time":0.1667,"x":0.01,"y":1.93},{"time":0.2333,"curve":"stepped"},{"time":0.5333},{"time":0.7333,"x":0.01,"y":1.93},{"time":0.9333}]},"yz":{"translate":[{"time":0.1667},{"time":0.2333,"x":-3.15},{"time":0.5333,"x":-21.5},{"time":0.7333,"x":5},{"time":0.9333}],"scale":[{},{"time":0.1667,"y":1.1},{"time":0.2333},{"time":0.5333,"y":0.9},{"time":0.7333,"y":1.1},{"time":0.9333}]},"bone6":{"rotate":[{},{"time":0.1667,"angle":9.49},{"time":0.2333,"angle":3.5,"curve":"stepped"},{"time":0.5333,"angle":3.5},{"time":0.7333,"angle":9.49},{"time":0.9333}],"translate":[{},{"time":0.1667,"x":-2.11,"y":-0.5},{"time":0.2333,"curve":"stepped"},{"time":0.5333},{"time":0.7333,"x":-2.11,"y":-0.5},{"time":0.9333}]},"bone3":{"rotate":[{},{"time":0.1667,"angle":2.73},{"time":0.2333,"angle":12.4},{"time":0.5333,"angle":22.01},{"time":0.7333,"angle":2.73},{"time":0.9333}]},"PET6016_zuotui1":{"rotate":[{},{"time":0.1667,"angle":-8.27},{"time":0.2333,"angle":-0.83},{"time":0.5333,"angle":-3.24},{"time":0.7333,"angle":-8.27},{"time":0.9333}],"translate":[{},{"time":0.1667,"x":0.9,"y":1.87},{"time":0.2333,"x":-4.07,"y":-4.73,"curve":"stepped"},{"time":0.5333,"x":-4.07,"y":-4.73},{"time":0.7333,"x":0.9,"y":1.87},{"time":0.9333}]},"PET6016_datui2":{"rotate":[{},{"time":0.1667,"angle":-4.31},{"time":0.2333,"curve":"stepped"},{"time":0.5333},{"time":0.7333,"angle":-4.31},{"time":0.9333}],"translate":[{},{"time":0.1667,"y":0.63},{"time":0.2333,"curve":"stepped"},{"time":0.5333},{"time":0.7333,"y":0.63},{"time":0.9333}]},"bone2":{"rotate":[{},{"time":0.1667,"angle":12.38},{"time":0.2333,"angle":-3.52,"curve":"stepped"},{"time":0.5333,"angle":-3.52},{"time":0.7333,"angle":12.38},{"time":0.9333}]},"PET6016_youtui2":{"rotate":[{},{"time":0.1667,"angle":3.65},{"time":0.2333,"angle":-2.17},{"time":0.5333,"angle":-4.57},{"time":0.7333,"angle":3.65},{"time":0.9333}],"translate":[{},{"time":0.1667,"x":-0.71,"y":-0.17},{"time":0.2333,"curve":"stepped"},{"time":0.5333},{"time":0.7333,"x":-0.71,"y":-0.17},{"time":0.9333}]},"PET6016_shengti":{"rotate":[{},{"time":0.1667,"angle":-2.59},{"time":0.2333,"angle":16.82},{"time":0.5333,"angle":18.56},{"time":0.7333,"angle":-2.59},{"time":0.9333}]},"bone4":{"rotate":[{},{"time":0.1667,"angle":17.33},{"time":0.5333,"angle":-5.25},{"time":0.7333,"angle":17.33},{"time":0.9333}]},"PET6016_zuoer":{"rotate":[{},{"time":0.1667,"angle":13.46},{"time":0.5333,"angle":-28.35},{"time":0.7333,"angle":13.46},{"time":0.9333}]}}},"skill01":{"slots":{"PET6016_zuikaixin":{"attachment":[{"time":0.2667,"name":"PET6016_zuibizui"},{"time":1.2333,"name":"PET6016_zuigongji"},{"time":2.1667,"name":"PET6016_zuikaixin"}]},"PET6016_lianjia1":{"color":[{"color":"ffffff00"},{"time":1.2333,"color":"ffffffff"},{"time":1.3333,"color":"ffffff00"},{"time":1.5667,"color":"ffffffff"},{"time":1.6333,"color":"ffffff00"}],"attachment":[{"time":1.2333,"name":"PET6016_lianjia2"},{"time":2.1667,"name":"PET6016_lianjia1"}]},"PET6016_yanjingputong":{"attachment":[{"time":0.2667,"name":"PET6016_yanjingxuli"},{"time":1.2333,"name":"PET6016_yanjinggongji"},{"time":2.1667,"name":"PET6016_yanjingputong"}]}},"bones":{"PET6016_weiba1":{"rotate":[{},{"time":0.2667,"angle":12.38},{"time":0.6333,"angle":61.35},{"time":0.9,"angle":71.25},{"time":1.2,"angle":61.35},{"time":1.2333,"angle":-47.62},{"time":1.3333,"angle":-21.86},{"time":1.4333,"angle":-43.11},{"time":1.5333,"angle":-32.25},{"time":1.6333,"angle":-36.48},{"time":1.7333,"angle":-32.25},{"time":1.8333,"angle":-36.48},{"time":1.9333,"angle":-32.25},{"time":2.0333,"angle":-36.48},{"time":2.1667}]},"PET6016_youtui2":{"rotate":[{},{"time":0.2667,"angle":-3},{"time":0.4,"angle":11.32},{"time":0.6333,"angle":16.1},{"time":0.9,"angle":18.65},{"time":1.2,"angle":16.1},{"time":1.2333,"angle":-3.24,"curve":"stepped"},{"time":1.9,"angle":-3.24},{"time":2.1667}],"translate":[{},{"time":0.2667,"x":2.99,"y":-1.94},{"time":0.4,"x":-1.66,"y":-1.6},{"time":0.6333,"x":-3.21,"y":-1.49},{"time":0.9,"x":-3.59,"y":-1.59},{"time":1.2,"x":-3.21,"y":-1.49},{"time":1.2333}]},"bone":{"translate":[{},{"time":0.2667,"x":5},{"time":0.4,"x":-6.24,"y":-2.25},{"time":0.6333,"x":-10,"y":-3,"curve":"stepped"},{"time":1.2,"x":-10,"y":-3},{"time":1.2333,"x":7,"y":1},{"time":1.9,"x":8,"y":2},{"time":2.1667}]},"bone4":{"rotate":[{},{"time":0.2667,"angle":8.96},{"time":0.4667,"angle":-8.5},{"time":0.6333,"angle":2.52},{"time":0.9,"angle":-9.13},{"time":1.2,"angle":2.52},{"time":1.2333,"angle":0.2},{"time":1.3333,"angle":-16.42},{"time":1.4333,"angle":4.79},{"time":1.5333,"angle":-11.76},{"time":1.6333,"angle":-1.88},{"time":1.7333,"angle":-11.76},{"time":1.8333,"angle":-1.88},{"time":1.9333,"angle":-11.76},{"time":2.0333,"angle":-1.88},{"time":2.1667}]},"PET6016_shengti":{"rotate":[{},{"time":0.2667,"angle":2.22},{"time":0.4,"angle":-7.43},{"time":0.6333,"angle":-10.65},{"time":0.9,"angle":-8.81},{"time":1.2,"angle":-10.65},{"time":1.2333,"angle":-2.19,"curve":"stepped"},{"time":1.9,"angle":-2.19},{"time":2.1667}]},"bone9":{"rotate":[{},{"time":0.2667,"angle":-24.06},{"time":0.6333,"angle":-37.27},{"time":0.9,"angle":-27.37},{"time":1.2,"angle":-37.27},{"time":1.2333,"angle":-2.04,"curve":"stepped"},{"time":2.0333,"angle":-2.04},{"time":2.1667}]},"PET6016_datui2":{"rotate":[{"time":0.2667},{"time":0.4,"angle":8.15},{"time":0.6333,"angle":10.87},{"time":0.9,"angle":9.31},{"time":1.2,"angle":10.87},{"time":1.2333,"angle":1.05},{"time":1.9,"angle":3.45},{"time":2.1667}],"translate":[{"time":0.2667},{"time":0.4,"x":0.3,"y":1.58},{"time":0.6333,"x":0.4,"y":2.11},{"time":0.9,"x":0.34,"y":1.81},{"time":1.2,"x":0.4,"y":2.11},{"time":1.2333,"x":-2.24,"y":-1.84},{"time":1.9,"x":-3.06,"y":-1.99},{"time":2.1667}]},"bone5":{"rotate":[{},{"time":0.2667,"angle":16.69},{"time":0.4667,"angle":-7.45},{"time":0.6333,"angle":19.84},{"time":0.9,"angle":4.27},{"time":1.2,"angle":19.84},{"time":1.2333,"angle":4.22},{"time":1.3333,"angle":-13.05},{"time":1.4333,"angle":7.53},{"time":1.5333,"angle":-5.45},{"time":1.6333,"angle":3.15},{"time":1.7333,"angle":-5.45},{"time":1.8333,"angle":3.15},{"time":1.9333,"angle":-5.45},{"time":2.0333,"angle":3.15},{"time":2.1667}]},"PET6016_zuoshoubi":{"rotate":[{},{"time":0.2667,"angle":-26.26},{"time":0.4,"angle":4.82},{"time":0.6333,"angle":15.18},{"time":0.9,"angle":10.27},{"time":1.2,"angle":15.18},{"time":1.2333,"angle":-15.81},{"time":1.9,"angle":-21.5},{"time":2.1667}],"translate":[{},{"time":0.2667,"x":-2.9,"y":1.21},{"time":0.4,"x":-0.71,"y":1.75},{"time":0.6333,"x":0.01,"y":1.93},{"time":0.9,"x":-0.4,"y":1.83},{"time":1.2,"x":0.01,"y":1.93},{"time":1.2333}]},"yz":{"translate":[{"time":0.2667},{"time":0.6333,"x":-7},{"time":0.9,"x":-4.45},{"time":1.2,"x":-7},{"time":1.2333,"x":5.08},{"time":1.9,"x":3.53},{"time":2.1667}],"scale":[{},{"time":0.2667,"y":1.1,"curve":"stepped"},{"time":0.6333,"y":1.1},{"time":0.9,"y":1.05},{"time":1.2,"y":1.1},{"time":1.2333},{"time":1.9,"y":0.9},{"time":2.1667}]},"PET6016_youshoubi":{"rotate":[{},{"time":0.2667,"angle":-27},{"time":0.4,"angle":2.42},{"time":0.6333,"angle":12.23},{"time":0.9,"angle":-2.82},{"time":1.2,"angle":12.23},{"time":1.2333,"angle":-18.76},{"time":1.9,"angle":-30.03},{"time":2.1667}],"translate":[{},{"time":0.2667,"x":1.26,"y":-3.78},{"time":0.4,"x":-0.74,"y":0.29},{"time":0.6333,"x":-1.41,"y":1.65,"curve":"stepped"},{"time":1.2,"x":-1.41,"y":1.65},{"time":1.2333},{"time":1.9,"x":0.9,"y":-0.3},{"time":2.1667}]},"PET6016_zuoer":{"rotate":[{},{"time":0.2667,"angle":16.69},{"time":0.4667,"angle":-7.45},{"time":0.6333,"angle":19.84},{"time":0.9,"angle":4.27},{"time":1.2,"angle":19.84},{"time":1.2333,"angle":-23.62},{"time":1.3333,"angle":-36.49},{"time":1.4333,"angle":-11.51},{"time":1.5333,"angle":-37.46},{"time":1.6333,"angle":-22.44},{"time":1.7333,"angle":-37.46},{"time":1.8333,"angle":-22.44},{"time":1.9333,"angle":-37.46},{"time":2.0333,"angle":-22.44},{"time":2.1667}]},"bone7":{"rotate":[{},{"time":0.2667,"angle":5.85},{"time":0.4,"angle":15.88},{"time":0.6333,"angle":19.22},{"time":0.9,"angle":17.31},{"time":1.2,"angle":19.22},{"time":1.2333,"angle":3.18,"curve":"stepped"},{"time":1.9,"angle":3.18},{"time":2.1667}],"translate":[{"time":0.2667},{"time":0.4,"x":0.01,"y":0.45},{"time":0.6333,"x":0.02,"y":0.6},{"time":0.9,"x":0.01,"y":0.51},{"time":1.2,"x":0.02,"y":0.6},{"time":1.2333}]},"PET6016_youer":{"rotate":[{},{"time":0.2667,"angle":8.96},{"time":0.4667,"angle":-8.5},{"time":0.6333,"angle":2.52},{"time":0.9,"angle":-9.13},{"time":1.2,"angle":2.52},{"time":1.2333,"angle":-57.09},{"time":1.3333,"angle":-64.68},{"time":1.4333,"angle":-34.41},{"time":1.5333,"angle":-70.28},{"time":1.6333,"angle":-48.7},{"time":1.7333,"angle":-70.28},{"time":1.8333,"angle":-48.7},{"time":1.9333,"angle":-70.28},{"time":2.0333,"angle":-48.7},{"time":2.1667}]},"PET6016_tou":{"rotate":[{},{"time":0.2667,"angle":5.2},{"time":0.4,"angle":9.17},{"time":0.6333,"angle":9.2},{"time":0.9,"angle":15.58},{"time":1.2,"angle":5.06},{"time":1.2333},{"time":1.9,"angle":2.69},{"time":2.1667}],"translate":[{},{"time":0.2667,"x":2.31,"y":1.38},{"time":0.4,"x":-0.31,"y":2.93,"curve":"stepped"},{"time":1.2,"x":-0.31,"y":2.93},{"time":1.2333}]},"bone6":{"rotate":[{},{"time":0.2667,"angle":18.48},{"time":0.4,"angle":15.09},{"time":0.6333,"angle":13.97},{"time":0.9,"angle":14.61},{"time":1.2,"angle":13.97},{"time":1.2333,"angle":13.82,"curve":"stepped"},{"time":1.9,"angle":13.82},{"time":2.1667}],"translate":[{"time":0.2667},{"time":0.4,"x":-1.58,"y":-0.37},{"time":0.6333,"x":-2.11,"y":-0.5},{"time":0.9,"x":-1.81,"y":-0.42},{"time":1.2,"x":-2.11,"y":-0.5},{"time":1.2333}]},"bone2":{"rotate":[{},{"time":0.2667,"angle":-9.02},{"time":0.4,"angle":7.02},{"time":0.6333,"angle":12.38},{"time":0.9,"angle":9.32},{"time":1.2,"angle":12.38},{"time":1.2333,"angle":-20.72,"curve":"stepped"},{"time":1.9,"angle":-20.72},{"time":2.1667}]},"PET6016_zuotui1":{"rotate":[{},{"time":0.2667,"angle":5.73},{"time":0.4,"angle":0.23},{"time":0.6333,"angle":-1.59},{"time":0.9,"angle":-0.54},{"time":1.2,"angle":-1.59},{"time":1.2333}],"translate":[{},{"time":0.2667,"x":-4.04,"y":1.46},{"time":0.4,"x":5.32,"y":3.33},{"time":0.6333,"x":8.44,"y":3.95},{"time":0.9,"x":6.66,"y":3.6},{"time":1.2,"x":8.44,"y":3.95},{"time":1.2333}]},"bone8":{"rotate":[{},{"time":0.2667,"angle":-8.42},{"time":0.4,"angle":12.04},{"time":0.6333,"angle":18.86},{"time":0.9,"angle":14.96},{"time":1.2,"angle":18.86},{"time":1.2333}]},"bone3":{"rotate":[{},{"time":0.2667,"angle":9.95},{"time":0.4,"angle":5.7},{"time":0.6333,"angle":4.29},{"time":0.9,"angle":9.74},{"time":1.2,"angle":4.29},{"time":1.2333,"angle":8.44},{"time":1.9,"angle":11.45},{"time":2.1667}]},"fs":{"translate":[{"x":-11.61,"y":16.53,"curve":"stepped"},{"time":1.2,"x":-11.61,"y":16.53},{"time":1.2333,"x":21.76,"y":32.14}]}}},"stand":{"slots":{"PET6016_lianjia1":{"color":[{"color":"ffffff00"}]},"PET6016_yanjingputong":{"attachment":[{"time":0.6667,"name":"PET6016_yanjingbiyan"},{"time":1,"name":"PET6016_yanjingputong"}]}},"bones":{"PET6016_weiba1":{"rotate":[{},{"time":0.2333,"angle":-4.3},{"time":0.5},{"time":0.7333,"angle":5.39},{"time":1}]},"PET6016_zuikaixin":{"scale":[{},{"time":0.5,"x":0.8},{"time":1}]},"bone":{"translate":[{},{"time":0.5,"y":-3},{"time":1}]},"PET6016_datui2":{"rotate":[{},{"time":0.5,"angle":-4.31},{"time":1}],"translate":[{},{"time":0.5,"y":0.63},{"time":1}]},"PET6016_shengti":{"rotate":[{},{"time":0.5,"angle":-2.59},{"time":1}]},"PET6016_youtui2":{"rotate":[{},{"time":0.5,"angle":3.65},{"time":1}],"translate":[{},{"time":0.5,"x":-0.71,"y":-0.17},{"time":1}]},"PET6016_zuotui1":{"rotate":[{},{"time":0.5,"angle":-8.27},{"time":1}],"translate":[{},{"time":0.5,"x":0.9,"y":1.87},{"time":1}]},"bone3":{"rotate":[{},{"time":0.5,"angle":2.73},{"time":1}]},"PET6016_tou":{"rotate":[{},{"time":0.2,"angle":5.26},{"time":0.5},{"time":0.7333,"angle":-4.95},{"time":1}]},"PET6016_youshoubi":{"rotate":[{},{"time":0.5,"angle":4.82},{"time":1}],"translate":[{},{"time":0.5,"x":-1.41,"y":1.65},{"time":1}]},"PET6016_zuoshoubi":{"rotate":[{},{"time":0.5,"angle":-3.89},{"time":1}],"translate":[{},{"time":0.5,"x":0.01,"y":1.93},{"time":1}]},"bone2":{"rotate":[{},{"time":0.5,"angle":12.38},{"time":1}]},"bone8":{"rotate":[{},{"time":0.5,"angle":18.86},{"time":1}]},"bone9":{"rotate":[{},{"time":0.2333,"angle":-9.23},{"time":0.5},{"time":0.7333,"angle":16.02},{"time":1}]},"PET6016_youer":{"rotate":[{},{"time":0.2,"angle":-12.79},{"time":0.5,"angle":6.57},{"time":0.6667,"angle":11.78},{"time":1}]},"PET6016_zuoer":{"rotate":[{},{"time":0.2667,"angle":3.26},{"time":0.5,"angle":-7.04},{"time":0.6667,"angle":-15.61},{"time":1}]},"bone6":{"rotate":[{},{"time":0.5,"angle":9.49},{"time":1}],"translate":[{},{"time":0.5,"x":-2.11,"y":-0.5},{"time":1}]},"bone7":{"rotate":[{},{"time":0.5,"angle":-3.68},{"time":1}],"translate":[{},{"time":0.5,"x":0.02,"y":0.6},{"time":1}]},"bone4":{"rotate":[{},{"time":0.2,"angle":-13.73},{"time":0.5,"angle":6.31},{"time":0.6667,"angle":18.38},{"time":1}]},"bone5":{"rotate":[{},{"time":0.2667,"angle":7.65},{"time":0.5,"angle":-4.28},{"time":0.6667,"angle":-13.77},{"time":1}]},"yz":{"scale":[{},{"time":0.5,"y":1.1},{"time":1}]}}},"walk":{"slots":{"PET6016_lianjia1":{"color":[{"color":"ffffff00"}]},"PET6016_yanjingputong":{"attachment":[{"time":0.4667,"name":"PET6016_yanjingbiyan"},{"time":0.7333,"name":"PET6016_yanjingputong"}]}},"bones":{"PET6016_weiba1":{"rotate":[{"angle":34.9},{"time":0.1667,"angle":13.71},{"time":0.3667,"angle":24.88},{"time":0.5333,"angle":40.11},{"time":0.7333,"angle":34.9}]},"PET6016_zuikaixin":{"scale":[{"time":0.3667},{"time":0.5667,"x":0.8},{"time":0.7333}]},"bone7":{"rotate":[{"angle":9.74},{"time":0.1667,"angle":1.79},{"time":0.3667,"angle":27.43},{"time":0.5333,"angle":57.86},{"time":0.7333,"angle":9.74}]},"bone5":{"rotate":[{"angle":17.23},{"time":0.1667,"angle":-7.52},{"time":0.3667,"angle":-10.68},{"time":0.5333,"angle":20.68},{"time":0.7333,"angle":-0.9}]},"bone6":{"rotate":[{"angle":6.21},{"time":0.1667,"angle":2.22},{"time":0.3667,"angle":34.72},{"time":0.5333,"angle":37.55},{"time":0.7333,"angle":6.21}]},"PET6016_youer":{"rotate":[{"angle":4.04},{"time":0.1667,"angle":-24.81},{"time":0.3667,"angle":5.44},{"time":0.5333,"angle":14.91},{"time":0.7333}]},"PET6016_youshoubi":{"rotate":[{"angle":14.16},{"time":0.1667,"angle":-7.07},{"time":0.3667,"angle":-48.42},{"time":0.5333,"angle":-8},{"time":0.7333,"angle":14.16}],"translate":[{},{"time":0.1667,"x":-1.54,"y":5.96},{"time":0.3667,"x":-4.72,"y":5.92},{"time":0.5333}]},"PET6016_youtui2":{"rotate":[{"angle":-13.44},{"time":0.1667,"angle":-72.36},{"time":0.3667,"curve":"stepped"},{"time":0.5333},{"time":0.7333,"angle":-13.44}]},"PET6016_zuotui1":{"rotate":[{"angle":-25.53},{"time":0.1667,"angle":-4.3},{"time":0.3667,"angle":42.14},{"time":0.5333,"angle":-3.72},{"time":0.7333,"angle":-25.53}],"translate":[{"time":0.3667},{"time":0.5333,"x":-9.58,"y":-1.54},{"time":0.7333}]},"yz":{"scale":[{"y":0.8},{"time":0.3667,"y":1.1},{"time":0.7333,"y":0.8}]},"PET6016_zuoshoubi":{"rotate":[{"angle":24.53},{"time":0.1667,"angle":10.06},{"time":0.3667,"angle":-20.25},{"time":0.5333,"angle":20.49},{"time":0.7333,"angle":24.53}],"translate":[{},{"time":0.1667,"x":3.22,"y":-3.87},{"time":0.3667}]},"PET6016_datui2":{"rotate":[{"angle":335.72},{"time":0.1667,"angle":27.99},{"time":0.3667,"angle":50.2},{"time":0.5333,"angle":-0.61},{"time":0.7333,"angle":335.72}],"translate":[{"x":-0.16,"y":-1.28},{"time":0.1667,"x":-4.86,"y":-0.4},{"time":0.3667,"x":-3.22,"y":1.56},{"time":0.5333},{"time":0.7333,"x":-0.16,"y":-1.28}]},"bone8":{"rotate":[{"angle":-21.14},{"time":0.1667,"angle":29.18},{"time":0.3667},{"time":0.5333,"angle":-23.88},{"time":0.7333,"angle":-21.14}]},"bone4":{"rotate":[{"angle":4.04},{"time":0.1667,"angle":-13.4},{"time":0.3667,"angle":-21.29},{"time":0.5333,"angle":28.85},{"time":0.7333}]},"PET6016_shengti":{"rotate":[{},{"time":0.1667,"angle":2.49},{"time":0.3667},{"time":0.5333,"angle":0.88},{"time":0.7333}],"translate":[{"time":0.3667},{"time":0.5333,"x":-0.13,"y":-3.58},{"time":0.7333}]},"PET6016_zuoer":{"rotate":[{"angle":23.33},{"time":0.1667,"angle":-6.08},{"time":0.3667,"angle":26.9},{"time":0.5333,"angle":38.99},{"time":0.7333,"angle":23.33}]},"bone3":{"rotate":[{"angle":12.06},{"time":0.1667,"angle":-2.47},{"time":0.3667},{"time":0.5333,"angle":18.84},{"time":0.7333,"angle":12.06}]},"bone9":{"rotate":[{"angle":-2.67},{"time":0.1667,"angle":23.58},{"time":0.3667,"angle":31.76},{"time":0.5333,"angle":-22.64},{"time":0.7333,"angle":-2.67}]},"PET6016_tou":{"rotate":[{"angle":6.34},{"time":0.1667,"angle":4.87},{"time":0.3667,"angle":6.33},{"time":0.5333},{"time":0.7333,"angle":6.34}]},"bone":{"rotate":[{"angle":-3.2},{"time":0.1667,"angle":-10.2},{"time":0.3667},{"time":0.5333,"angle":2.18},{"time":0.7333,"angle":-3.2}],"translate":[{"x":7.49,"y":20},{"time":0.1667,"x":8,"y":5},{"time":0.3667},{"time":0.5333,"y":10},{"time":0.7333,"x":7.49,"y":20}]},"bone2":{"rotate":[{"angle":-32.39},{"time":0.1667,"angle":46.68},{"time":0.3667,"angle":0.97},{"time":0.5333,"angle":-27.26},{"time":0.7333,"angle":-32.39}]}}},"win":{"slots":{"PET6016_zuikaixin":{"attachment":[{"time":0.2333,"name":"PET6016_zuibizui"},{"time":1.2,"name":"PET6016_zuikaixin"}]},"PET6016_lianjia1":{"color":[{"color":"ffffff00"}]},"PET6016_yanjingputong":{"attachment":[{"time":0.2333,"name":"PET6016_yanjingbiyan"},{"time":0.4,"name":"PET6016_yanjingputong"}]}},"bones":{"PET6016_weiba1":{"rotate":[{},{"time":0.2333,"angle":10.33},{"time":0.4,"angle":63.68},{"time":0.4667,"angle":73.49},{"time":0.5333,"angle":62.29},{"time":0.7,"angle":59.88},{"time":0.8667,"angle":69.31},{"time":0.9333,"angle":56.5},{"time":1,"angle":10.33},{"time":1.2}]},"PET6016_youshoubi":{"rotate":[{},{"time":0.2333,"angle":12.23},{"time":0.3333,"angle":5.29},{"time":0.8667,"angle":-3.08},{"time":0.9333,"angle":36.11},{"time":1,"angle":12.23},{"time":1.2}],"translate":[{},{"time":0.2333,"x":-1.41,"y":1.65},{"time":0.3333},{"time":1,"x":-1.41,"y":1.65},{"time":1.2}]},"bone6":{"rotate":[{},{"time":0.2333,"angle":45.46},{"time":0.3333,"angle":3.5},{"time":0.8667,"angle":12.24},{"time":0.9333,"angle":11.55},{"time":1,"angle":45.46},{"time":1.2}],"translate":[{},{"time":0.2333,"x":-2.11,"y":-0.5},{"time":0.3333},{"time":1,"x":-2.11,"y":-0.5},{"time":1.2}]},"bone7":{"rotate":[{},{"time":0.2333,"angle":19.22},{"time":0.3333,"angle":5.29},{"time":0.8667,"angle":-11.89},{"time":0.9333,"angle":-2.67},{"time":1,"angle":19.22},{"time":1.2}],"translate":[{},{"time":0.2333,"x":0.02,"y":0.6},{"time":0.3333},{"time":1,"x":0.02,"y":0.6},{"time":1.2}]},"PET6016_youer":{"rotate":[{},{"time":0.2333,"angle":15.14},{"time":0.3333,"angle":3.39},{"time":0.7,"angle":5.14},{"time":0.8667,"angle":20.85},{"time":1,"angle":15.14},{"time":1.2}]},"PET6016_zuoer":{"rotate":[{},{"time":0.2333,"angle":20.56},{"time":0.3333,"angle":17.27},{"time":0.4667,"angle":29.11},{"time":0.7,"angle":25.37},{"time":0.8667,"angle":37.61},{"time":1,"angle":20.56},{"time":1.2}]},"bone4":{"rotate":[{},{"time":0.2333,"angle":14.88},{"time":0.3333,"angle":3.13},{"time":0.7,"angle":4.88},{"time":0.8667,"angle":20.59},{"time":1,"angle":14.88},{"time":1.2}]},"PET6016_tou":{"rotate":[{},{"time":0.2333,"angle":-2.75},{"time":0.3333,"angle":-4.21},{"time":0.8667,"angle":-11.68},{"time":0.9333,"angle":-4.25},{"time":1,"angle":-2.75},{"time":1.2}]},"yz":{"translate":[{},{"time":0.3333,"x":-3.15},{"time":0.4333,"x":3.23,"y":0.54},{"time":0.5333,"x":-14.71,"y":0.47},{"time":0.6333,"x":-15.94,"y":0.54},{"time":0.7333,"x":-4.85,"y":0.47},{"time":0.8667,"x":-0.17,"y":0.34},{"time":1,"x":-0.1,"y":0.2},{"time":1.2}],"scale":[{},{"time":0.2333,"y":1.1},{"time":0.3333},{"time":0.4333,"y":0.7},{"time":0.5333,"y":0.9},{"time":0.6333,"y":0.7},{"time":0.7333,"y":0.9},{"time":0.8667,"y":0.8},{"time":1,"y":1.1},{"time":1.2}]},"bone3":{"rotate":[{},{"time":0.2333,"angle":4.29},{"time":0.3333,"angle":27.9},{"time":0.4,"angle":52.64},{"time":0.4333,"angle":57.68},{"time":0.4667,"angle":64.93},{"time":0.5,"angle":52.09},{"time":0.5333,"angle":65.93},{"time":0.5667,"angle":46.23},{"time":0.6,"angle":69.53},{"time":0.6667,"angle":61.55},{"time":0.8667,"angle":19.67},{"time":0.9333,"angle":43.56},{"time":1,"angle":4.29},{"time":1.2}]},"PET6016_zuotui1":{"rotate":[{},{"time":0.2333,"angle":-8.27},{"time":0.3333,"angle":-5.35},{"time":0.4,"angle":-37.04},{"time":0.4667,"angle":-28.77},{"time":0.5333,"angle":-25.01},{"time":0.8667,"angle":0.44},{"time":1,"angle":-8.27},{"time":1.2}],"translate":[{},{"time":0.2333,"x":0.9,"y":1.87},{"time":0.3333,"x":-4.07,"y":-4.73},{"time":1,"x":0.9,"y":1.87},{"time":1.2}]},"bone9":{"rotate":[{},{"time":0.2333,"angle":10.33},{"time":0.4,"angle":-6.78},{"time":0.4667,"angle":-21.2},{"time":0.5333,"angle":-13.04},{"time":0.7,"angle":-18.58},{"time":0.8667,"angle":-12.28},{"time":0.9333,"angle":-26.34},{"time":1,"angle":10.33},{"time":1.2}]},"PET6016_shengti":{"rotate":[{},{"time":0.2333,"angle":-10.65},{"time":0.3333,"angle":16.82},{"time":0.4,"angle":2.54},{"time":0.4333,"angle":-7.32},{"time":0.4667,"angle":4.73},{"time":0.5333,"angle":12.93},{"time":0.6,"angle":17.52},{"time":0.8667,"angle":30.6},{"time":0.9333,"angle":22.58},{"time":1,"angle":-10.65},{"time":1.2}]},"PET6016_datui2":{"rotate":[{},{"time":0.2333,"angle":-4.31},{"time":0.3333},{"time":0.8667,"angle":25.46},{"time":1,"angle":-4.31},{"time":1.2}],"translate":[{},{"time":0.2333,"y":0.63},{"time":0.3333},{"time":0.8667,"x":-2.09,"y":-0.19},{"time":1,"y":0.63},{"time":1.2}]},"bone":{"rotate":[{"time":0.4},{"time":0.4667,"angle":69.74},{"time":0.5333,"angle":158.37},{"time":0.6,"angle":-89.23},{"time":0.6667,"angle":-37.04},{"time":0.8667,"angle":-33.24},{"time":0.9333,"angle":-54.28},{"time":1}],"translate":[{},{"time":0.2333,"y":-3},{"time":0.3333,"x":-1.57},{"time":0.4,"x":26.26,"y":51.22},{"time":0.4333,"x":44.98,"y":104.14},{"time":0.4667,"x":53.1,"y":143.51},{"time":0.5333,"x":-47.22,"y":168.47},{"time":0.6,"x":-53.54,"y":75.46},{"time":0.6667,"x":-5.14,"y":78.88},{"time":0.8667,"x":0.48,"y":110.07},{"time":0.9333,"x":-4.05,"y":91.25},{"time":0.9667,"x":0.58,"y":56.65},{"time":1,"y":-3},{"time":1.2}]},"bone8":{"rotate":[{},{"time":0.2333,"angle":18.86},{"time":0.3333,"angle":-15.49},{"time":0.4,"angle":-47.18},{"time":0.5333,"angle":-35.16},{"time":0.8667,"angle":-9.69},{"time":1,"angle":18.86},{"time":1.2}]},"bone5":{"rotate":[{},{"time":0.2333,"angle":24.94},{"time":0.3333,"angle":17.99},{"time":0.7,"angle":21.81},{"time":0.8667,"angle":38.47},{"time":1,"angle":24.94},{"time":1.2}]},"PET6016_zuoshoubi":{"rotate":[{},{"time":0.2333,"angle":-11.52},{"time":0.3333,"angle":20.1},{"time":0.4667,"angle":22.99},{"time":0.8667,"angle":8.02},{"time":0.9333,"angle":46},{"time":1,"angle":-11.52},{"time":1.2}],"translate":[{},{"time":0.2333,"x":0.01,"y":1.93},{"time":0.3333},{"time":1,"x":0.01,"y":1.93},{"time":1.2}]},"PET6016_youtui2":{"rotate":[{},{"time":0.2333,"angle":16.1},{"time":0.3333,"angle":-6.06},{"time":0.4,"angle":-37.75},{"time":0.5333,"angle":-25.72},{"time":0.8667,"angle":-23.75},{"time":0.9333,"angle":-12.12},{"time":1,"angle":16.1},{"time":1.2}],"translate":[{},{"time":0.2333,"x":-0.71,"y":-0.17},{"time":0.3333},{"time":1,"x":-0.71,"y":-0.17},{"time":1.2}]},"bone2":{"rotate":[{},{"time":0.2333,"angle":12.38},{"time":0.3333,"angle":-7.41},{"time":0.4,"angle":-39.1},{"time":0.5333,"angle":-27.08},{"time":0.8667,"angle":-8.02},{"time":0.9333,"angle":0.1},{"time":1,"angle":12.38},{"time":1.2}]}}}}}